{
    "os": "Linux-5.4.0-172-generic-x86_64-with-glibc2.35",
    "python": "3.10.13",
    "heartbeatAt": "2024-03-01T14:53:06.562139",
    "startedAt": "2024-03-01T14:53:05.873099",
    "docker": null,
    "cuda": null,
    "args": [
        "eval",
        "--checkpoint",
        "models/TCN-99-springset-20240229-073453-16kHz.pt"
    ],
    "state": "running",
    "program": "/root/neural-audio-spring-reverb/.venv/bin/nafx-springrev",
    "codePathLocal": ".venv/bin/nafx-springrev",
    "codePath": ".venv/bin/nafx-springrev",
    "git": {
        "remote": "https://github.com/francescopapaleo/neural-audio-spring-reverb.git",
        "commit": "f108e7930941184eeae879eaf953046287cf5138"
    },
    "email": "francesco.papaleo@gmail.com",
    "root": "/root/neural-audio-spring-reverb",
    "host": "b9138d24f869",
    "username": "root",
    "executable": "/root/neural-audio-spring-reverb/.venv/bin/python3",
    "cpu_count": 8,
    "cpu_count_logical": 16,
    "cpu_freq": {
        "current": 1579.1098749999999,
        "min": 1500.0,
        "max": 3100.0
    },
    "cpu_freq_per_core": [
        {
            "current": 1499.742,
            "min": 1500.0,
            "max": 3100.0
        },
        {
            "current": 1495.053,
            "min": 1500.0,
            "max": 3100.0
        },
        {
            "current": 1499.792,
            "min": 1500.0,
            "max": 3100.0
        },
        {
            "current": 1499.698,
            "min": 1500.0,
            "max": 3100.0
        },
        {
            "current": 1402.439,
            "min": 1500.0,
            "max": 3100.0
        },
        {
            "current": 1997.949,
            "min": 1500.0,
            "max": 3100.0
        },
        {
            "current": 1494.607,
            "min": 1500.0,
            "max": 3100.0
        },
        {
            "current": 1498.835,
            "min": 1500.0,
            "max": 3100.0
        },
        {
            "current": 1499.903,
            "min": 1500.0,
            "max": 3100.0
        },
        {
            "current": 1499.72,
            "min": 1500.0,
            "max": 3100.0
        },
        {
            "current": 1675.213,
            "min": 1500.0,
            "max": 3100.0
        },
        {
            "current": 1499.761,
            "min": 1500.0,
            "max": 3100.0
        },
        {
            "current": 1369.39,
            "min": 1500.0,
            "max": 3100.0
        },
        {
            "current": 2401.699,
            "min": 1500.0,
            "max": 3100.0
        },
        {
            "current": 1432.357,
            "min": 1500.0,
            "max": 3100.0
        },
        {
            "current": 1499.6,
            "min": 1500.0,
            "max": 3100.0
        }
    ],
    "disk": {
        "/": {
            "total": 16.0,
            "used": 11.870052337646484
        }
    },
    "gpu": "NVIDIA RTX A5000",
    "gpu_count": 1,
    "gpu_devices": [
        {
            "name": "NVIDIA RTX A5000",
            "memory_total": 25757220864
        }
    ],
    "memory": {
        "total": 440.5736961364746
    }
}
